LICENSE
README.md
setup.py
id_region/__init__.py
id_region/data.py
id_region/get_info.py
id_region/helper.py
id_region.egg-info/PKG-INFO
id_region.egg-info/SOURCES.txt
id_region.egg-info/dependency_links.txt
id_region.egg-info/top_level.txt