Metadata-Version: 2.1
Name: id-region
Version: 0.0.1
Summary: find id region from id card
Home-page: https://github.com/hbx286/id-region.git
Author: hbx286
Author-email: hbxmail429@gmail.com
License: MIT
Classifier: License :: OSI Approved :: MIT License
Classifier: Programming Language :: Python
Classifier: Programming Language :: Python :: 3
Classifier: Programming Language :: Python :: 3.6
Classifier: Programming Language :: Python :: Implementation :: CPython
Classifier: Programming Language :: Python :: Implementation :: PyPy
Requires-Python: >=3.8.0
License-File: LICENSE
